{
  "description": "Pica demo app for the Polymer UI toolkit",
  "archive_data_file": "data/pica.json",
  "pages": [
    { "url": "http://localhost/polymer/projects/pica/",
      "script_to_evaluate_on_commit":
          "document.addEventListener('polymer-ready', function(){var unused = document.body.offsetHeight; window.__pica_load_time = performance.now(); setTimeout(function(){window.__polymer_ready=true}, 1000)})",
      "navigate_steps" : [
        { "action": "navigate" },
        { "action": "wait", "javascript": "window.__polymer_ready" }
      ]
    }
  ]
}
