[
  {
    "namespace": "experimental.accessibility",
    "nodoc": true,
    "types": [
      {
        "id": "AccessibilityObject",
        "type": "object",
        "description": "Parent class for accessibility information about an object.",
        "properties": {
          "type": {
            "type": "string",
            "description": "The type of this object, which determines the contents of 'details'.",
            "enum": ["button", "checkbox", "combobox", "link", "menu", "menuitem", "radiobutton", "tab", "textbox", "window"]
          },
          "name": {
            "type": "string",
            "description": "The localized name of the object, like OK or Password. Do not rely on an exact string match because the text will be in the user's language and may change in the future."
          },
          "context": {
            "type": "string",
            "description": "The localized name of the context for the object, like the name of the surrounding toolbar or group of controls.",
            "optional": true
          },
          "details": {
            "description": "Other details like the state, depending on the type of object.",
            "optional": true,
            "choices": [
              { "$ref": "CheckboxDetails" },
              { "$ref": "ComboBoxDetails" },
              { "$ref": "MenuDetails" },
              { "$ref": "MenuItemDetails" },
              { "$ref": "RadioButtonDetails" },
              { "$ref": "TabDetails" },
              { "$ref": "TextBoxDetails" }
            ]
          }
        }
      },
      {
        "id": "CheckboxDetails",
        "type": "object",
        "description": "Information about the state of a checkbox.",
        "properties": {
          "isChecked": {"type": "boolean", "description": "True if this checkbox is checked."}
        }
      },
      {
        "id": "ComboBoxDetails",
        "type": "object",
        "description": "Information about the state of a combo box.",
        "properties": {
          "value": {"type": "string", "description": "The value of the combo box."},
          "itemCount": {"type": "integer", "description": "The number of items in the combo box's list."},
          "itemIndex": {"type": "integer", "description": "The 0-based index of the current value, or -1 if the user entered a value not from the list."}
        }
      },
      {
        "id": "ListBoxDetails",
        "type": "object",
        "description": "Information about the state of a list box.",
        "properties": {
          "value": {"type": "string", "description": "The value of the list box."},
          "itemCount": {"type": "integer", "description": "The number of items in the list."},
          "itemIndex": {"type": "integer", "description": "The 0-based index of the selected value, or -1 if no items are selected."}
        }
      },
      {
        "id": "MenuDetails",
        "type": "object",
        "description": "Information about the state of a drop-down menu.",
        "properties": {
        }
      },
      {
        "id": "MenuItemDetails",
        "type": "object",
        "description": "Information about a menu item.",
        "properties": {
          "hasSubmenu": {"type": "boolean", "description": "True if this item opens a submenu."},
          "itemCount": {"type": "integer", "description": "The number of items in the menu."},
          "itemIndex": {"type": "integer", "description": "The 0-based index of this menu item."}
        }
      },
      {
        "id": "RadioButtonDetails",
        "type": "object",
        "description": "Information about the state of a radio button.",
        "properties": {
          "isChecked": {"type": "boolean", "description": "True if this radio button is checked."},
          "itemCount": {"type": "integer", "description": "The number of radio buttons in this group."},
          "itemIndex": {"type": "integer", "description": "The 0-based index of this radio button in this group."}
        }
      },
      {
        "id": "TabDetails",
        "type": "object",
        "description": "Additional accessibility information about a tab.",
        "properties": {
          "itemCount": {"type": "integer", "description": "The number of tabs in this group."},
          "itemIndex": {"type": "integer", "description": "The 0-based index of this tab in this group."}
        }
      },
      {
        "id": "TextBoxDetails",
        "type": "object",
        "description": "Information about the state of a text box.",
        "properties": {
          "value": {"type": "string", "description": "The value of the text box - the entered text."},
          "isPassword": {"type": "boolean", "description": "True if this control contains password text whose contents should be obscured."},
          "selectionStart": {"type": "integer", "description": "The index of the character where the selection starts, if this control contains editable text."},
          "selectionEnd": {"type": "integer", "description": "The index of the character where the selection ends, if this control contains editable text."}
        }
      },
      {
        "id": "AccessibilityVolumeInfo",
        "type": "object",
        "description": "Information about the volume.",
        "properties": {
          "volume": {"type": "double", "description": "The value of the volume percent. This must be between 0.0 and 100.0."},
          "isVolumeMuted": {"type": "boolean", "description": "True if the volume is muted."}
        }
      }
    ],
    "functions": [
      {
        "name": "setAccessibilityEnabled",
        "type": "function",
        "description": "Enables or disables the accessibility extension api. This must be set to true before event listeners or getFocusedControl will work.",
        "parameters": [
          {
            "type": "boolean",
            "name": "enabled",
            "description": "True if accessibility support should be enabled."
          }
        ]
      },
      {
        "name": "getFocusedControl",
        "type": "function",
        "description": "Gets information about the currently focused control.",
        "parameters": [
          {
            "type": "function",
            "name": "callback",
            "parameters": [
              {
                "name": "control",
                "description": "Details of the currently focused control, or null if nothing is focused.",
                "choices": [
                  { "$ref": "AccessibilityObject" },
                  { "type": "null" }
                ]
              }
            ]
          }
        ]
      }
    ],
    "events": [
      {
        "name": "onWindowOpened",
        "type": "function",
        "description": "Fired when a window is opened.",
        "parameters": [
          {
            "$ref": "AccessibilityObject",
            "name": "window",
            "description": "Information about the window that was opened."
          }
        ]
      },
      {
        "name": "onWindowClosed",
        "type": "function",
        "description": "Fired when a window is closed.",
        "parameters": [
          {
            "$ref": "AccessibilityObject",
            "name": "window",
            "description": "Information about the window that was closed."
          }
        ]
      },
      {
        "name": "onControlFocused",
        "type": "function",
        "description": "Fired when a control is focused.",
        "parameters": [
          {
            "$ref": "AccessibilityObject",
            "name": "control",
            "description": "Details of the control that was focused."
          }
        ]
      },
      {
        "name": "onControlAction",
        "type": "function",
        "description": "Fired when a control's action is taken, like pressing a button or toggling a checkbox.",
        "parameters": [
          {
            "$ref": "AccessibilityObject",
            "name": "control",
            "description": "Details of the control whose action was taken."
          }
        ]
      },
      {
        "name": "onTextChanged",
        "type": "function",
        "description": "Fired when text changes in an editable text control.",
        "parameters": [
          {
            "$ref": "AccessibilityObject",
            "name": "control",
            "description": "Details of the control where the text changed."
          }
        ]
      },
      {
        "name": "onMenuOpened",
        "type": "function",
        "description": "Fired when a menu is opened.",
        "parameters": [
          {
            "$ref": "AccessibilityObject",
            "name": "menu",
            "description": "Information about the menu that was opened."
          }
        ]
      },
      {
        "name": "onMenuClosed",
        "type": "function",
        "description": "Fired when a menu is closed.",
        "parameters": [
          {
            "$ref": "AccessibilityObject",
            "name": "menu",
            "description": "Information about the menu that was closed."
          }
        ]
      },
      {
        "name": "onVolumeChanged",
        "type": "function",
        "description": "Fired when the volume is changed.",
        "parameters": [
          {
            "$ref": "AccessibilityVolumeInfo",
            "name": "volume",
            "description": "Information about the current state of the system volume control, including whether it is muted."
          }
        ]
      },
      {
        "name": "onScreenUnlocked",
        "type": "function",
        "description": "Fired when the screen is unlocked.",
        "parameters": []
      },
      {
        "name": "onWokeUp",
        "type": "function",
        "description": "Fired when the device wakes up from sleep.",
        "parameters": []
      }
    ]
  }
]
